regexify/__init__.py
regexify/pattern.py
regexify/pattern_trie.py
regexify-0.2.1.dist-info/LICENSE
regexify-0.2.1.dist-info/WHEEL
regexify-0.2.1.dist-info/METADATA
regexify-0.2.1.dist-info/RECORD
