Metadata-Version: 2.1
Name: regexify
Version: 0.2.1
Summary: Regular expression containers and helper functions to simplify the use and deployment of regular expressions.
Home-page: https://github.com/dcronkite/regexify
Author: dcronkite
Author-email: dcronkite+pypi@gmail.com
Requires-Python: >=3.7
Classifier: License :: OSI Approved :: MIT License
Classifier: Development Status :: 4 - Beta
Classifier: Programming Language :: Python :: 3 :: Only
